buicap_py/__init__.py
buicap_py/_core.py
buicap_py/api.py
buicap_py/const.py
buicap_py/error_codes.py
buicap_py/exceptions.py
buicap_py/py.typed
buicap_py-0.1.2.dist-info/licenses/LICENSE
buicap_py-0.1.2.dist-info/METADATA
buicap_py-0.1.2.dist-info/WHEEL
buicap_py-0.1.2.dist-info/top_level.txt
buicap_py-0.1.2.dist-info/RECORD
