Metadata-Version: 2.4
Name: buicap-py
Version: 0.1.2
Summary: Python wrapper for Digital Check DLL
Author-email: Alexis Ocando <alexisocando.cl@gmail.com>
License: MIT License
Project-URL: Homepage, https://github.com/tomjod/buicap-py
Project-URL: Issues, https://github.com/tomjod/buicap-py/issues
Classifier: Programming Language :: Python :: 3
Classifier: Operating System :: Microsoft :: Windows
Requires-Python: >=3.8
License-File: LICENSE
Dynamic: license-file
